esy/osm/shape/__init__.py
esy/osm/shape/index.py
esy/osm/shape/mpl.py
esy/osm/shape/shape.py
esy/osm/shape/test.py
esy_osm_shape-0.4.dist-info/licenses/LICENSE
esy_osm_shape-0.4.dist-info/METADATA
esy_osm_shape-0.4.dist-info/WHEEL
esy_osm_shape-0.4.dist-info/top_level.txt
esy_osm_shape-0.4.dist-info/RECORD
