Metadata-Version: 2.4
Name: esy-osm-shape
Version: 0.4
Summary: Convert OpenStreetMap primitives to shapely objects
Author-email: Ontje Lünsdorf <ontje.luensdorf@dlr.de>
License: BSD-3-Clause
Project-URL: homepage, https://gitlab.com/dlr-ve-esy/esy-osm-shape
Project-URL: documentation, https://dlr-ve-esy.gitlab.io/esy-osm-shape
Keywords: OSM,OpenStreetMap,shapely
Classifier: Development Status :: 5 - Production/Stable
Classifier: Environment :: Console
Classifier: Intended Audience :: Developers
Classifier: Intended Audience :: Education
Classifier: Intended Audience :: Science/Research
Classifier: License :: OSI Approved :: BSD License
Classifier: Natural Language :: English
Classifier: Operating System :: OS Independent
Classifier: Programming Language :: Python
Classifier: Programming Language :: Python :: 3
Classifier: Topic :: Scientific/Engineering
Requires-Python: >=3.5
License-File: LICENSE
Requires-Dist: shapely>=1.6
Requires-Dist: esy-osm-pbf>=0.1
Provides-Extra: dev
Requires-Dist: matplotlib; extra == "dev"
Requires-Dist: pdoc; extra == "dev"
Requires-Dist: pyproj>=3; extra == "dev"
Dynamic: license-file
